MANIFEST.in
dev_requirements.txt
requirements.txt
setup.py
test_requirements.txt
version.txt
cloudshell/__init__.py
cloudshell/firewall/__init__.py
cloudshell/firewall/a10/__init__.py
cloudshell/firewall/a10/autoload/__init__.py
cloudshell/firewall/a10/autoload/a10_snmp_autoload.py
cloudshell/firewall/a10/cli/__init__.py
cloudshell/firewall/a10/cli/a10_cli_handler.py
cloudshell/firewall/a10/cli/a10_command_modes.py
cloudshell/firewall/a10/command_actions/__init__.py
cloudshell/firewall/a10/command_actions/enable_disable_snmp_actions.py
cloudshell/firewall/a10/command_actions/system_actions.py
cloudshell/firewall/a10/command_templates/__init__.py
cloudshell/firewall/a10/command_templates/configuration.py
cloudshell/firewall/a10/command_templates/enable_disable_snmp.py
cloudshell/firewall/a10/flows/__init__.py
cloudshell/firewall/a10/flows/a10_autoload_flow.py
cloudshell/firewall/a10/flows/a10_disable_snmp_flow.py
cloudshell/firewall/a10/flows/a10_enable_snmp_flow.py
cloudshell/firewall/a10/flows/a10_load_firmware_flow.py
cloudshell/firewall/a10/flows/a10_restore_flow.py
cloudshell/firewall/a10/flows/a10_save_flow.py
cloudshell/firewall/a10/helpers/__init__.py
cloudshell/firewall/a10/helpers/exceptions.py
cloudshell/firewall/a10/mibs/A10-AX-MIB.py
cloudshell/firewall/a10/mibs/A10-COMMON-MIB.py
cloudshell/firewall/a10/mibs/IP-MIB.py
cloudshell/firewall/a10/mibs/IPV6-MIB.py
cloudshell/firewall/a10/mibs/__init__.py
cloudshell/firewall/a10/runners/__init__.py
cloudshell/firewall/a10/runners/a10_autoload_runner.py
cloudshell/firewall/a10/runners/a10_configuration_runner.py
cloudshell/firewall/a10/runners/a10_firmware_runner.py
cloudshell/firewall/a10/snmp/__init__.py
cloudshell/firewall/a10/snmp/a10_snmp_handler.py
cloudshell_firewall_a10.egg-info/PKG-INFO
cloudshell_firewall_a10.egg-info/SOURCES.txt
cloudshell_firewall_a10.egg-info/dependency_links.txt
cloudshell_firewall_a10.egg-info/requires.txt
cloudshell_firewall_a10.egg-info/top_level.txt
tests/__init__.py
tests/firewall/__init__.py
tests/firewall/a10/__init__.py
tests/firewall/a10/base_test.py
tests/firewall/a10/test_cli.py
tests/firewall/a10/test_load_firmware.py
tests/firewall/a10/test_restore_config.py
tests/firewall/a10/test_save_config.py
