Metadata-Version: 1.0
Name: cloudshell-firewall-a10
Version: 1.0.0
Summary: QualiSystems firewall A10 specific package
Home-page: http://www.qualisystems.com/
Author: QualiSystems
Author-email: info@qualisystems.com
License: UNKNOWN
Platform: UNKNOWN
